.gitignore
README.md
deploy.sh
setup.cfg
setup.py
bin/waboxapp
waboxapp/__init__.py
waboxapp.egg-info/PKG-INFO
waboxapp.egg-info/SOURCES.txt
waboxapp.egg-info/dependency_links.txt
waboxapp.egg-info/top_level.txt