Metadata-Version: 1.1
Name: waboxapp
Version: 0.1
Summary: Waboxapp library for accessing waboxapp.com api
Home-page: https://github.com/cristianowa/waboxapp
Author: Cristiano W. Araujo
Author-email: cristianowerneraraujo@gmail.com
License: UNKNOWN
Download-URL: https://github.com/cristianowa/waboxapp/archive/0.1.zip
Keywords: whatsup,waboxapp,instant message
Platform: UNKNOWN
